{
    "bg-color-primary": "rgba(255,255,255,0.25)",
    
    "ui-color-primary": "rgba(255,255,255,0.5)",
    "ui-color-secondary": "rgba(255,255,255,0.25)",
    "ui-color-tertiary": "rgba(255,255,255,0.25)",
    "ui-color-quaternary": "rgba(255,255,255,0.25)",

    "navbar-color": "rgba(255,255,255,0.25)",

    "active": "#3883c9",
    "inactive": "#5f5f5f",

    "successful": "#18cded",
    "unsuccessful": "#d93a6f",
    "banner-ui-color": "rgba(25,25,25,0.4)",

    "heading-color-1": "#000",
    "paragraph-color-1": "#262626",

    "active-outline-thickness": "0.5vmin",
    "global-border-radius": "1vmin",
    "global-transition-time": "0.35s",

    "background-image": "none",
    "background-image-blur": "1vmin",

    "font": "'JetBrains Mono', sans-serif"
}
